[{"bench":{"namespaces":[{"name":"gold","chart":{"Name":"my-app","DirPath":"/exp/conf/helm/exp2app"},"config":{"Settings":[{"Parameter":{"Name":"worker1CPU","Resource":"","Searchspace":{"Min":2200,"Max":2200,"Granularity":1},"Prefix":"","Suffix":"m"},"Value":{"Value":2200,"Type":"int"}},{"Parameter":{"Name":"worker1Replicas","Resource":"","Searchspace":{"Min":0,"Max":0,"Granularity":1},"Prefix":"","Suffix":""},"Value":{"Value":0,"Type":"int"}},{"Parameter":{"Name":"worker2CPU","Resource":"","Searchspace":{"Min":750,"Max":750,"Granularity":1},"Prefix":"","Suffix":"m"},"Value":{"Value":750,"Type":"int"}},{"Parameter":{"Name":"worker2Replicas","Resource":"","Searchspace":{"Min":1,"Max":1,"Granularity":1},"Prefix":"","Suffix":""},"Value":{"Value":1,"Type":"int"}},{"Parameter":{"Name":"worker3CPU","Resource":"","Searchspace":{"Min":250,"Max":250,"Granularity":1},"Prefix":"","Suffix":"m"},"Value":{"Value":250,"Type":"int"}},{"Parameter":{"Name":"worker3Replicas","Resource":"","Searchspace":{"Min":0,"Max":2,"Granularity":1},"Prefix":"","Suffix":""},"Value":{"Value":2,"Type":"int"}},{"Parameter":{"Name":"demoCPU","Resource":"","Searchspace":{"Min":800,"Max":800,"Granularity":100},"Prefix":"","Suffix":"m"},"Value":{"Value":800,"Type":"int"}}]}}],"experiment":{"Iteration":0,"Sample":0,"Locustconfig":{"Name":"","ScriptPath":"/tmp/locustwrap/locust_exp.py","Users":4,"HatchRate":4,"DurationInSeconds":60},"OutputDir":"/exp/Results/exp3/gold/4_tenants-ex1/exh/","Type":"LocustBatchExperiment"}},"result":{"Results":{"name":"","Distribution":[{"Name":"GET gold-0","# requests":"21","50%":"2700","66%":"3600","75%":"3600","80%":"3800","90%":"4800","95%":"5000","98%":"5100","99%":"5100","100%":"5100"},{"Name":"GET gold-1","# requests":"19","50%":"3500","66%":"3700","75%":"4400","80%":"4800","90%":"5000","95%":"5100","98%":"5100","99%":"5100","100%":"5100"},{"Name":"GET gold-2","# requests":"23","50%":"2600","66%":"3200","75%":"3600","80%":"3700","90%":"4800","95%":"5000","98%":"5500","99%":"5500","100%":"5500"},{"Name":"GET gold-3","# requests":"24","50%":"2400","66%":"3200","75%":"3700","80%":"3800","90%":"4700","95%":"4900","98%":"5000","99%":"5000","100%":"5000"},{"Name":"Total","# requests":"87","50%":"2600","66%":"3500","75%":"3700","80%":"3800","90%":"4900","95%":"5000","98%":"5100","99%":"5500","100%":"5500"}],"Requests":[{"Name":"gold-0","# failures":"0","Max response time":"5133","Median response time":"2700","Average response time":"2820","Min response time":"495","Method":"GET","Requests/s":"0.36","# requests":"21","Average Content Size":"19"},{"Name":"gold-1","# failures":"0","Max response time":"5070","Median response time":"3500","Average response time":"3094","Min response time":"700","Method":"GET","Requests/s":"0.32","# requests":"19","Average Content Size":"19"},{"Name":"gold-2","# failures":"0","Max response time":"5481","Median response time":"2600","Average response time":"2547","Min response time":"732","Method":"GET","Requests/s":"0.39","# requests":"23","Average Content Size":"19"},{"Name":"gold-3","# failures":"0","Max response time":"4986","Median response time":"2300","Average response time":"2451","Min response time":"423","Method":"GET","Requests/s":"0.41","# requests":"24","Average Content Size":"19"},{"Name":"Total","# failures":"0","Max response time":"5481","Median response time":"2600","Average response time":"2706","Min response time":"423","Method":"None","Requests/s":"1.48","# requests":"87","Average Content Size":"19"}],"Duration":121239602194},"Type":"LocustBatchExperimentResult"}},{"bench":{"namespaces":[{"name":"gold","chart":{"Name":"my-app","DirPath":"/exp/conf/helm/exp2app"},"config":{"Settings":[{"Parameter":{"Name":"worker1CPU","Resource":"","Searchspace":{"Min":2200,"Max":2200,"Granularity":1},"Prefix":"","Suffix":"m"},"Value":{"Value":2200,"Type":"int"}},{"Parameter":{"Name":"worker1Replicas","Resource":"","Searchspace":{"Min":0,"Max":0,"Granularity":1},"Prefix":"","Suffix":""},"Value":{"Value":0,"Type":"int"}},{"Parameter":{"Name":"worker2CPU","Resource":"","Searchspace":{"Min":750,"Max":750,"Granularity":1},"Prefix":"","Suffix":"m"},"Value":{"Value":750,"Type":"int"}},{"Parameter":{"Name":"worker2Replicas","Resource":"","Searchspace":{"Min":1,"Max":1,"Granularity":1},"Prefix":"","Suffix":""},"Value":{"Value":1,"Type":"int"}},{"Parameter":{"Name":"worker3CPU","Resource":"","Searchspace":{"Min":250,"Max":250,"Granularity":1},"Prefix":"","Suffix":"m"},"Value":{"Value":250,"Type":"int"}},{"Parameter":{"Name":"worker3Replicas","Resource":"","Searchspace":{"Min":0,"Max":2,"Granularity":1},"Prefix":"","Suffix":""},"Value":{"Value":0,"Type":"int"}},{"Parameter":{"Name":"demoCPU","Resource":"","Searchspace":{"Min":800,"Max":800,"Granularity":100},"Prefix":"","Suffix":"m"},"Value":{"Value":800,"Type":"int"}}]}}],"experiment":{"Iteration":0,"Sample":2,"Locustconfig":{"Name":"","ScriptPath":"/tmp/locustwrap/locust_exp.py","Users":4,"HatchRate":4,"DurationInSeconds":60},"OutputDir":"/exp/Results/exp3/gold/4_tenants-ex1/op/","Type":"LocustBatchExperiment"}},"result":{"Results":{"name":"","Distribution":[{"Name":"GET gold-0","# requests":"51","50%":"1200","66%":"1400","75%":"1500","80%":"1600","90%":"1600","95%":"1800","98%":"2000","99%":"2100","100%":"2100"},{"Name":"GET gold-1","# requests":"24","50%":"1500","66%":"1500","75%":"1600","80%":"1600","90%":"1800","95%":"1900","98%":"1900","99%":"1900","100%":"1900"},{"Name":"GET gold-2","# requests":"21","50%":"1500","66%":"1600","75%":"1600","80%":"1600","90%":"1800","95%":"2200","98%":"2700","99%":"2700","100%":"2700"},{"Name":"GET gold-3","# requests":"50","50%":"1200","66%":"1400","75%":"1500","80%":"1500","90%":"1700","95%":"1800","98%":"2000","99%":"2000","100%":"2000"},{"Name":"Total","# requests":"146","50%":"1400","66%":"1500","75%":"1500","80%":"1600","90%":"1700","95%":"1900","98%":"2100","99%":"2200","100%":"2700"}],"Requests":[{"Name":"gold-0","# failures":"0","Max response time":"2062","Median response time":"1200","Average response time":"1167","Min response time":"408","Method":"GET","Requests/s":"0.86","# requests":"51","Average Content Size":"19"},{"Name":"gold-1","# failures":"0","Max response time":"1912","Median response time":"1400","Average response time":"1464","Min response time":"876","Method":"GET","Requests/s":"0.4","# requests":"24","Average Content Size":"19"},{"Name":"gold-2","# failures":"0","Max response time":"2670","Median response time":"1500","Average response time":"1568","Min response time":"1064","Method":"GET","Requests/s":"0.35","# requests":"21","Average Content Size":"19"},{"Name":"gold-3","# failures":"0","Max response time":"1961","Median response time":"1200","Average response time":"1178","Min response time":"466","Method":"GET","Requests/s":"0.84","# requests":"50","Average Content Size":"19"},{"Name":"Total","# failures":"0","Max response time":"2670","Median response time":"1400","Average response time":"1277","Min response time":"408","Method":"None","Requests/s":"2.46","# requests":"146","Average Content Size":"19"}],"Duration":121083422910},"Type":"LocustBatchExperimentResult"}},{"bench":{"namespaces":[{"name":"gold","chart":{"Name":"my-app","DirPath":"/exp/conf/helm/exp2app"},"config":{"Settings":[{"Parameter":{"Name":"worker1CPU","Resource":"","Searchspace":{"Min":2200,"Max":2200,"Granularity":1},"Prefix":"","Suffix":"m"},"Value":{"Value":2200,"Type":"int"}},{"Parameter":{"Name":"worker1Replicas","Resource":"","Searchspace":{"Min":0,"Max":0,"Granularity":1},"Prefix":"","Suffix":""},"Value":{"Value":0,"Type":"int"}},{"Parameter":{"Name":"worker2CPU","Resource":"","Searchspace":{"Min":750,"Max":750,"Granularity":1},"Prefix":"","Suffix":"m"},"Value":{"Value":750,"Type":"int"}},{"Parameter":{"Name":"worker2Replicas","Resource":"","Searchspace":{"Min":1,"Max":1,"Granularity":1},"Prefix":"","Suffix":""},"Value":{"Value":1,"Type":"int"}},{"Parameter":{"Name":"worker3CPU","Resource":"","Searchspace":{"Min":250,"Max":250,"Granularity":1},"Prefix":"","Suffix":"m"},"Value":{"Value":250,"Type":"int"}},{"Parameter":{"Name":"worker3Replicas","Resource":"","Searchspace":{"Min":0,"Max":2,"Granularity":1},"Prefix":"","Suffix":""},"Value":{"Value":1,"Type":"int"}},{"Parameter":{"Name":"demoCPU","Resource":"","Searchspace":{"Min":800,"Max":800,"Granularity":100},"Prefix":"","Suffix":"m"},"Value":{"Value":800,"Type":"int"}}]}}],"experiment":{"Iteration":0,"Sample":2,"Locustconfig":{"Name":"","ScriptPath":"/tmp/locustwrap/locust_exp.py","Users":4,"HatchRate":4,"DurationInSeconds":60},"OutputDir":"/exp/Results/exp3/gold/4_tenants-ex1/op/","Type":"LocustBatchExperiment"}},"result":{"Results":{"name":"","Distribution":[{"Name":"GET gold-0","# requests":"33","50%":"1300","66%":"1800","75%":"1900","80%":"2000","90%":"4100","95%":"5100","98%":"5300","99%":"5300","100%":"5300"},{"Name":"GET gold-1","# requests":"31","50%":"1400","66%":"2000","75%":"2300","80%":"2300","90%":"4400","95%":"4500","98%":"5800","99%":"5800","100%":"5800"},{"Name":"GET gold-2","# requests":"24","50%":"2000","66%":"3600","75%":"4200","80%":"4300","90%":"4900","95%":"5300","98%":"5300","99%":"5300","100%":"5300"},{"Name":"GET gold-3","# requests":"26","50%":"1700","66%":"3000","75%":"3700","80%":"4000","90%":"4700","95%":"5300","98%":"5700","99%":"5700","100%":"5700"},{"Name":"Total","# requests":"114","50%":"1500","66%":"2000","75%":"3000","80%":"3700","90%":"4600","95%":"5300","98%":"5300","99%":"5700","100%":"5800"}],"Requests":[{"Name":"gold-0","# failures":"0","Max response time":"5291","Median response time":"1300","Average response time":"1780","Min response time":"442","Method":"GET","Requests/s":"0.56","# requests":"33","Average Content Size":"19"},{"Name":"gold-1","# failures":"0","Max response time":"5800","Median response time":"1400","Average response time":"1885","Min response time":"398","Method":"GET","Requests/s":"0.52","# requests":"31","Average Content Size":"19"},{"Name":"gold-2","# failures":"0","Max response time":"5330","Median response time":"1800","Average response time":"2473","Min response time":"643","Method":"GET","Requests/s":"0.41","# requests":"24","Average Content Size":"19"},{"Name":"gold-3","# failures":"0","Max response time":"5701","Median response time":"1600","Average response time":"2288","Min response time":"444","Method":"GET","Requests/s":"0.44","# requests":"26","Average Content Size":"19"},{"Name":"Total","# failures":"0","Max response time":"5800","Median response time":"1400","Average response time":"2070","Min response time":"398","Method":"None","Requests/s":"1.93","# requests":"114","Average Content Size":"19"}],"Duration":121284034039},"Type":"LocustBatchExperimentResult"}}]