[{"Name": "GET silver-0", "100%": "950", "50%": "250", "# requests": "167", "80%": "640", "99%": "940", "75%": "460", "90%": "680", "66%": "280", "95%": "700", "98%": "850"}, {"Name": "GET silver-1", "100%": "1000", "50%": "250", "# requests": "165", "80%": "660", "99%": "900", "75%": "450", "90%": "680", "66%": "270", "95%": "700", "98%": "760"}, {"Name": "Total", "100%": "1000", "50%": "250", "# requests": "332", "80%": "650", "99%": "900", "75%": "450", "90%": "680", "66%": "280", "95%": "700", "98%": "850"}]