[{"Name": "GET silver-0", "100%": "1800", "50%": "57", "# requests": "241", "80%": "500", "99%": "1400", "75%": "94", "90%": "1000", "66%": "71", "95%": "1000", "98%": "1400"}, {"Name": "GET silver-1", "100%": "1800", "50%": "57", "# requests": "237", "80%": "500", "99%": "1400", "75%": "110", "90%": "1000", "66%": "80", "95%": "1100", "98%": "1400"}, {"Name": "Total", "100%": "1800", "50%": "57", "# requests": "478", "80%": "500", "99%": "1400", "75%": "100", "90%": "1000", "66%": "76", "95%": "1100", "98%": "1400"}]