[{"# failures": "0", "Max response time": "1707", "Name": "gold-0", "Median response time": "1400", "Average response time": "1446", "# requests": "40", "Min response time": "1258", "Requests/s": "0.67", "Average Content Size": "19", "Method": "GET"}, {"# failures": "0", "Max response time": "1719", "Name": "gold-1", "Median response time": "1400", "Average response time": "1408", "# requests": "42", "Min response time": "350", "Requests/s": "0.70", "Average Content Size": "19", "Method": "GET"}, {"# failures": "0", "Max response time": "1716", "Name": "gold-2", "Median response time": "1400", "Average response time": "1421", "# requests": "41", "Min response time": "597", "Requests/s": "0.69", "Average Content Size": "19", "Method": "GET"}, {"# failures": "0", "Max response time": "1699", "Name": "gold-3", "Median response time": "1400", "Average response time": "1443", "# requests": "41", "Min response time": "1069", "Requests/s": "0.69", "Average Content Size": "19", "Method": "GET"}, {"# failures": "0", "Max response time": "1709", "Name": "gold-4", "Median response time": "1400", "Average response time": "1424", "# requests": "41", "Min response time": "557", "Requests/s": "0.69", "Average Content Size": "19", "Method": "GET"}, {"# failures": "0", "Max response time": "1700", "Name": "gold-5", "Median response time": "1400", "Average response time": "1434", "# requests": "41", "Min response time": "698", "Requests/s": "0.69", "Average Content Size": "19", "Method": "GET"}, {"# failures": "0", "Max response time": "1631", "Name": "gold-6", "Median response time": "1400", "Average response time": "1386", "# requests": "43", "Min response time": "299", "Requests/s": "0.72", "Average Content Size": "19", "Method": "GET"}, {"# failures": "0", "Max response time": "1705", "Name": "gold-7", "Median response time": "1400", "Average response time": "1451", "# requests": "40", "Min response time": "1284", "Requests/s": "0.67", "Average Content Size": "19", "Method": "GET"}, {"# failures": "0", "Max response time": "1719", "Name": "Total", "Median response time": "1400", "Average response time": "1426", "# requests": "329", "Min response time": "299", "Requests/s": "5.50", "Average Content Size": "19", "Method": "None"}]