[{"bench":{"namespaces":[{"name":"silver","chart":{"Name":"my-app","DirPath":"conf/helm/exp1app"},"config":{"Settings":[{"Parameter":{"Name":"workerCPU","Resource":"","Searchspace":{"Min":2200,"Max":2200,"Granularity":10},"Prefix":"","Suffix":"m"},"Value":{"Value":2200,"Type":"int"}},{"Parameter":{"Name":"workerReplicas","Resource":"","Searchspace":{"Min":1,"Max":1,"Granularity":1},"Prefix":"","Suffix":""},"Value":{"Value":1,"Type":"int"}},{"Parameter":{"Name":"demoCPU","Resource":"","Searchspace":{"Min":1000,"Max":1000,"Granularity":100},"Prefix":"","Suffix":"m"},"Value":{"Value":1000,"Type":"int"}}]}}],"experiment":{"Iteration":0,"Sample":0,"Locustconfig":{"Name":"","ScriptPath":"/tmp/locustwrap/locust_exp.py","Users":11,"HatchRate":11,"DurationInSeconds":60},"OutputDir":"Results/exp1_op/","Type":"LocustBatchExperiment"}},"result":{"Results":{"name":"","Distribution":[{"Name":"GET silver-0","# requests":"29","50%":"2000","66%":"2100","75%":"2100","80%":"2100","90%":"2200","95%":"2200","98%":"2300","99%":"2300","100%":"2300"},{"Name":"GET silver-1","# requests":"29","50%":"2000","66%":"2100","75%":"2100","80%":"2100","90%":"2200","95%":"2200","98%":"2400","99%":"2400","100%":"2400"},{"Name":"GET silver-10","# requests":"29","50%":"2000","66%":"2100","75%":"2100","80%":"2100","90%":"2200","95%":"2200","98%":"2400","99%":"2400","100%":"2400"},{"Name":"GET silver-2","# requests":"29","50%":"2000","66%":"2100","75%":"2100","80%":"2100","90%":"2200","95%":"2200","98%":"2400","99%":"2400","100%":"2400"},{"Name":"GET silver-3","# requests":"29","50%":"2000","66%":"2100","75%":"2100","80%":"2200","90%":"2200","95%":"2300","98%":"2300","99%":"2300","100%":"2300"},{"Name":"GET silver-4","# requests":"29","50%":"2000","66%":"2100","75%":"2100","80%":"2200","90%":"2200","95%":"2200","98%":"2300","99%":"2300","100%":"2300"},{"Name":"GET silver-5","# requests":"29","50%":"2000","66%":"2100","75%":"2100","80%":"2100","90%":"2200","95%":"2300","98%":"2300","99%":"2300","100%":"2300"},{"Name":"GET silver-6","# requests":"29","50%":"2000","66%":"2100","75%":"2100","80%":"2100","90%":"2200","95%":"2200","98%":"2200","99%":"2200","100%":"2200"},{"Name":"GET silver-7","# requests":"29","50%":"2000","66%":"2100","75%":"2100","80%":"2100","90%":"2200","95%":"2200","98%":"2300","99%":"2300","100%":"2300"},{"Name":"GET silver-8","# requests":"29","50%":"2000","66%":"2100","75%":"2100","80%":"2200","90%":"2200","95%":"2200","98%":"2300","99%":"2300","100%":"2300"},{"Name":"GET silver-9","# requests":"29","50%":"2000","66%":"2100","75%":"2100","80%":"2100","90%":"2200","95%":"2300","98%":"2300","99%":"2300","100%":"2300"},{"Name":"Total","# requests":"319","50%":"2000","66%":"2100","75%":"2100","80%":"2100","90%":"2200","95%":"2200","98%":"2300","99%":"2300","100%":"2400"}],"Requests":[{"Name":"silver-0","# failures":"0","Max response time":"2265","Median response time":"2000","Average response time":"2027","Min response time":"1784","Method":"GET","Requests/s":"0.49","# requests":"29","Average Content Size":"19"},{"Name":"silver-1","# failures":"0","Max response time":"2399","Median response time":"2000","Average response time":"2031","Min response time":"1843","Method":"GET","Requests/s":"0.49","# requests":"29","Average Content Size":"19"},{"Name":"silver-10","# failures":"0","Max response time":"2359","Median response time":"2000","Average response time":"2030","Min response time":"1762","Method":"GET","Requests/s":"0.49","# requests":"29","Average Content Size":"19"},{"Name":"silver-2","# failures":"0","Max response time":"2364","Median response time":"2000","Average response time":"2023","Min response time":"1807","Method":"GET","Requests/s":"0.49","# requests":"29","Average Content Size":"19"},{"Name":"silver-3","# failures":"0","Max response time":"2299","Median response time":"2000","Average response time":"2006","Min response time":"1401","Method":"GET","Requests/s":"0.49","# requests":"29","Average Content Size":"19"},{"Name":"silver-4","# failures":"0","Max response time":"2294","Median response time":"2000","Average response time":"2017","Min response time":"1604","Method":"GET","Requests/s":"0.49","# requests":"29","Average Content Size":"19"},{"Name":"silver-5","# failures":"0","Max response time":"2284","Median response time":"2000","Average response time":"2001","Min response time":"1195","Method":"GET","Requests/s":"0.49","# requests":"29","Average Content Size":"19"},{"Name":"silver-6","# failures":"0","Max response time":"2248","Median response time":"2000","Average response time":"2017","Min response time":"1769","Method":"GET","Requests/s":"0.49","# requests":"29","Average Content Size":"19"},{"Name":"silver-7","# failures":"0","Max response time":"2296","Median response time":"2000","Average response time":"2020","Min response time":"1796","Method":"GET","Requests/s":"0.49","# requests":"29","Average Content Size":"19"},{"Name":"silver-8","# failures":"0","Max response time":"2315","Median response time":"2000","Average response time":"2006","Min response time":"1292","Method":"GET","Requests/s":"0.49","# requests":"29","Average Content Size":"19"},{"Name":"silver-9","# failures":"0","Max response time":"2279","Median response time":"2000","Average response time":"2010","Min response time":"1574","Method":"GET","Requests/s":"0.49","# requests":"29","Average Content Size":"19"},{"Name":"Total","# failures":"0","Max response time":"2399","Median response time":"2000","Average response time":"2017","Min response time":"1195","Method":"None","Requests/s":"5.39","# requests":"319","Average Content Size":"19"}],"Duration":121427273619},"Type":"LocustBatchExperimentResult"}}]