[{"Name": "GET gold-0", "100%": "6500", "50%": "3100", "# requests": "19", "80%": "4800", "99%": "6500", "75%": "4200", "90%": "5300", "66%": "3800", "95%": "6500", "98%": "6500"}, {"Name": "GET gold-1", "100%": "6400", "50%": "2400", "# requests": "24", "80%": "3600", "99%": "6400", "75%": "3300", "90%": "4800", "66%": "2700", "95%": "5400", "98%": "6400"}, {"Name": "GET gold-2", "100%": "5400", "50%": "2600", "# requests": "21", "80%": "4400", "99%": "5400", "75%": "3600", "90%": "4500", "66%": "3200", "95%": "4900", "98%": "5400"}, {"Name": "GET gold-3", "100%": "6500", "50%": "2300", "# requests": "23", "80%": "3900", "99%": "6500", "75%": "3700", "90%": "4300", "66%": "3300", "95%": "4500", "98%": "6500"}, {"Name": "GET gold-4", "100%": "6400", "50%": "2400", "# requests": "19", "80%": "3000", "99%": "6400", "75%": "2800", "90%": "5500", "66%": "2600", "95%": "6400", "98%": "6400"}, {"Name": "Total", "100%": "6500", "50%": "2600", "# requests": "106", "80%": "3900", "99%": "6500", "75%": "3600", "90%": "4800", "66%": "3200", "95%": "5400", "98%": "6400"}]