[{"# failures": "0", "Max response time": "1523", "Name": "silver-0", "Median response time": "270", "Average response time": "430", "# requests": "139", "Min response time": "220", "Requests/s": "2.32", "Average Content Size": "19", "Method": "GET"}, {"# failures": "0", "Max response time": "1569", "Name": "silver-1", "Median response time": "280", "Average response time": "429", "# requests": "138", "Min response time": "219", "Requests/s": "2.31", "Average Content Size": "19", "Method": "GET"}, {"# failures": "0", "Max response time": "1569", "Name": "Total", "Median response time": "270", "Average response time": "429", "# requests": "277", "Min response time": "219", "Requests/s": "4.63", "Average Content Size": "19", "Method": "None"}]