[{"Name": "GET silver-0", "100%": "2600", "50%": "91", "# requests": "98", "80%": "1600", "99%": "2600", "75%": "1500", "90%": "1700", "66%": "230", "95%": "2100", "98%": "2600"}, {"Name": "GET silver-1", "100%": "3000", "50%": "91", "# requests": "98", "80%": "1600", "99%": "3000", "75%": "1500", "90%": "2000", "66%": "200", "95%": "2300", "98%": "2700"}, {"Name": "Total", "100%": "3000", "50%": "91", "# requests": "196", "80%": "1600", "99%": "2700", "75%": "1500", "90%": "1800", "66%": "210", "95%": "2200", "98%": "2600"}]