[{"# failures": "0", "Max response time": "2801", "Name": "gold-0", "Median response time": "1200", "Average response time": "1409", "# requests": "41", "Min response time": "389", "Requests/s": "0.69", "Average Content Size": "19", "Method": "GET"}, {"# failures": "0", "Max response time": "2901", "Name": "gold-1", "Median response time": "1300", "Average response time": "1411", "# requests": "41", "Min response time": "402", "Requests/s": "0.69", "Average Content Size": "19", "Method": "GET"}, {"# failures": "0", "Max response time": "2591", "Name": "gold-2", "Median response time": "1400", "Average response time": "1528", "# requests": "39", "Min response time": "746", "Requests/s": "0.65", "Average Content Size": "19", "Method": "GET"}, {"# failures": "0", "Max response time": "3580", "Name": "gold-3", "Median response time": "1300", "Average response time": "1424", "# requests": "41", "Min response time": "371", "Requests/s": "0.69", "Average Content Size": "19", "Method": "GET"}, {"# failures": "0", "Max response time": "2668", "Name": "gold-4", "Median response time": "1400", "Average response time": "1488", "# requests": "40", "Min response time": "365", "Requests/s": "0.67", "Average Content Size": "19", "Method": "GET"}, {"# failures": "0", "Max response time": "3580", "Name": "Total", "Median response time": "1300", "Average response time": "1451", "# requests": "202", "Min response time": "365", "Requests/s": "3.39", "Average Content Size": "19", "Method": "None"}]