[{"# failures": "0", "Max response time": "1661", "Name": "silver-0", "Median response time": "270", "Average response time": "448", "# requests": "133", "Min response time": "225", "Requests/s": "2.24", "Average Content Size": "19", "Method": "GET"}, {"# failures": "0", "Max response time": "1589", "Name": "silver-1", "Median response time": "260", "Average response time": "445", "# requests": "133", "Min response time": "218", "Requests/s": "2.24", "Average Content Size": "19", "Method": "GET"}, {"# failures": "0", "Max response time": "1661", "Name": "Total", "Median response time": "270", "Average response time": "446", "# requests": "266", "Min response time": "218", "Requests/s": "4.48", "Average Content Size": "19", "Method": "None"}]