[{"# failures": "0", "Max response time": "6571", "Name": "silver-0", "Median response time": "4800", "Average response time": "4288", "# requests": "13", "Min response time": "1296", "Requests/s": "0.22", "Average Content Size": "19", "Method": "GET"}, {"# failures": "0", "Max response time": "7664", "Name": "silver-1", "Median response time": "4800", "Average response time": "4466", "# requests": "13", "Min response time": "1530", "Requests/s": "0.22", "Average Content Size": "19", "Method": "GET"}, {"# failures": "0", "Max response time": "6269", "Name": "silver-2", "Median response time": "4700", "Average response time": "4275", "# requests": "13", "Min response time": "1415", "Requests/s": "0.22", "Average Content Size": "19", "Method": "GET"}, {"# failures": "0", "Max response time": "8569", "Name": "silver-3", "Median response time": "4800", "Average response time": "4535", "# requests": "13", "Min response time": "1924", "Requests/s": "0.22", "Average Content Size": "19", "Method": "GET"}, {"# failures": "0", "Max response time": "7374", "Name": "silver-4", "Median response time": "4800", "Average response time": "4343", "# requests": "13", "Min response time": "1313", "Requests/s": "0.22", "Average Content Size": "19", "Method": "GET"}, {"# failures": "0", "Max response time": "8248", "Name": "silver-5", "Median response time": "4700", "Average response time": "4513", "# requests": "13", "Min response time": "2137", "Requests/s": "0.22", "Average Content Size": "19", "Method": "GET"}, {"# failures": "0", "Max response time": "8695", "Name": "silver-6", "Median response time": "4800", "Average response time": "4530", "# requests": "12", "Min response time": "1873", "Requests/s": "0.20", "Average Content Size": "19", "Method": "GET"}, {"# failures": "0", "Max response time": "7968", "Name": "silver-7", "Median response time": "4800", "Average response time": "4496", "# requests": "13", "Min response time": "1781", "Requests/s": "0.22", "Average Content Size": "19", "Method": "GET"}, {"# failures": "0", "Max response time": "6852", "Name": "silver-8", "Median response time": "4700", "Average response time": "4304", "# requests": "13", "Min response time": "1294", "Requests/s": "0.22", "Average Content Size": "19", "Method": "GET"}, {"# failures": "0", "Max response time": "7077", "Name": "silver-9", "Median response time": "4700", "Average response time": "4317", "# requests": "13", "Min response time": "1304", "Requests/s": "0.22", "Average Content Size": "19", "Method": "GET"}, {"# failures": "0", "Max response time": "8695", "Name": "Total", "Median response time": "4800", "Average response time": "4406", "# requests": "129", "Min response time": "1294", "Requests/s": "2.16", "Average Content Size": "19", "Method": "None"}]