[{"# failures": "0", "Max response time": "700", "Name": "silver-0", "Median response time": "240", "Average response time": "349", "# requests": "170", "Min response time": "137", "Requests/s": "2.87", "Average Content Size": "19", "Method": "GET"}, {"# failures": "0", "Max response time": "708", "Name": "silver-1", "Median response time": "240", "Average response time": "345", "# requests": "173", "Min response time": "123", "Requests/s": "2.92", "Average Content Size": "19", "Method": "GET"}, {"# failures": "0", "Max response time": "708", "Name": "Total", "Median response time": "240", "Average response time": "347", "# requests": "343", "Min response time": "123", "Requests/s": "5.79", "Average Content Size": "19", "Method": "None"}]