[{"# failures": "0", "Max response time": "2592", "Name": "gold-0", "Median response time": "1800", "Average response time": "1821", "# requests": "32", "Min response time": "835", "Requests/s": "0.54", "Average Content Size": "19", "Method": "GET"}, {"# failures": "0", "Max response time": "2997", "Name": "gold-1", "Median response time": "1900", "Average response time": "1872", "# requests": "31", "Min response time": "980", "Requests/s": "0.53", "Average Content Size": "19", "Method": "GET"}, {"# failures": "0", "Max response time": "2675", "Name": "gold-10", "Median response time": "1800", "Average response time": "1762", "# requests": "33", "Min response time": "873", "Requests/s": "0.56", "Average Content Size": "19", "Method": "GET"}, {"# failures": "0", "Max response time": "2968", "Name": "gold-2", "Median response time": "1900", "Average response time": "1925", "# requests": "30", "Min response time": "856", "Requests/s": "0.51", "Average Content Size": "19", "Method": "GET"}, {"# failures": "0", "Max response time": "2877", "Name": "gold-3", "Median response time": "1800", "Average response time": "1773", "# requests": "33", "Min response time": "723", "Requests/s": "0.56", "Average Content Size": "19", "Method": "GET"}, {"# failures": "0", "Max response time": "2901", "Name": "gold-4", "Median response time": "1600", "Average response time": "1719", "# requests": "34", "Min response time": "868", "Requests/s": "0.58", "Average Content Size": "19", "Method": "GET"}, {"# failures": "0", "Max response time": "2833", "Name": "gold-5", "Median response time": "1800", "Average response time": "1835", "# requests": "32", "Min response time": "832", "Requests/s": "0.54", "Average Content Size": "19", "Method": "GET"}, {"# failures": "0", "Max response time": "2572", "Name": "gold-6", "Median response time": "1800", "Average response time": "1792", "# requests": "33", "Min response time": "1012", "Requests/s": "0.56", "Average Content Size": "19", "Method": "GET"}, {"# failures": "0", "Max response time": "3094", "Name": "gold-7", "Median response time": "1800", "Average response time": "1790", "# requests": "33", "Min response time": "820", "Requests/s": "0.56", "Average Content Size": "19", "Method": "GET"}, {"# failures": "0", "Max response time": "2939", "Name": "gold-8", "Median response time": "1700", "Average response time": "1729", "# requests": "34", "Min response time": "1035", "Requests/s": "0.58", "Average Content Size": "19", "Method": "GET"}, {"# failures": "0", "Max response time": "2485", "Name": "gold-9", "Median response time": "1600", "Average response time": "1675", "# requests": "35", "Min response time": "974", "Requests/s": "0.60", "Average Content Size": "19", "Method": "GET"}, {"# failures": "0", "Max response time": "3094", "Name": "Total", "Median response time": "1800", "Average response time": "1788", "# requests": "360", "Min response time": "723", "Requests/s": "6.12", "Average Content Size": "19", "Method": "None"}]