[{"bench":{"namespaces":[{"name":"gold","chart":{"Name":"my-app","DirPath":"/exp/conf/helm/exp2app"},"config":{"Settings":[{"Parameter":{"Name":"worker1CPU","Resource":"","Searchspace":{"Min":2200,"Max":2200,"Granularity":1},"Prefix":"","Suffix":"m"},"Value":{"Value":2200,"Type":"int"}},{"Parameter":{"Name":"worker1Replicas","Resource":"","Searchspace":{"Min":0,"Max":0,"Granularity":1},"Prefix":"","Suffix":""},"Value":{"Value":0,"Type":"int"}},{"Parameter":{"Name":"worker2CPU","Resource":"","Searchspace":{"Min":750,"Max":750,"Granularity":1},"Prefix":"","Suffix":"m"},"Value":{"Value":750,"Type":"int"}},{"Parameter":{"Name":"worker2Replicas","Resource":"","Searchspace":{"Min":1,"Max":1,"Granularity":1},"Prefix":"","Suffix":""},"Value":{"Value":1,"Type":"int"}},{"Parameter":{"Name":"worker3CPU","Resource":"","Searchspace":{"Min":250,"Max":250,"Granularity":1},"Prefix":"","Suffix":"m"},"Value":{"Value":250,"Type":"int"}},{"Parameter":{"Name":"worker3Replicas","Resource":"","Searchspace":{"Min":0,"Max":1,"Granularity":1},"Prefix":"","Suffix":""},"Value":{"Value":0,"Type":"int"}},{"Parameter":{"Name":"demoCPU","Resource":"","Searchspace":{"Min":800,"Max":800,"Granularity":100},"Prefix":"","Suffix":"m"},"Value":{"Value":800,"Type":"int"}}]}}],"experiment":{"Iteration":0,"Sample":1,"Locustconfig":{"Name":"","ScriptPath":"/tmp/locustwrap/locust_exp.py","Users":2,"HatchRate":2,"DurationInSeconds":60},"OutputDir":"/exp/Results/exp3/gold/2_tenants-ex1/op/","Type":"LocustBatchExperiment"}},"result":{"Results":{"name":"","Distribution":[{"Name":"GET gold-0","# requests":"74","50%":"820","66%":"890","75%":"920","80%":"940","90%":"1000","95%":"1100","98%":"1200","99%":"1200","100%":"1200"},{"Name":"GET gold-1","# requests":"71","50%":"780","66%":"900","75%":"980","80%":"1000","90%":"1200","95%":"1300","98%":"1300","99%":"1400","100%":"1400"},{"Name":"Total","# requests":"145","50%":"810","66%":"900","75%":"930","80%":"970","90%":"1100","95%":"1200","98%":"1300","99%":"1300","100%":"1400"}],"Requests":[{"Name":"gold-0","# failures":"0","Max response time":"1238","Median response time":"810","Average response time":"807","Min response time":"341","Method":"GET","Requests/s":"1.24","# requests":"74","Average Content Size":"19"},{"Name":"gold-1","# failures":"0","Max response time":"1360","Median response time":"780","Average response time":"834","Min response time":"423","Method":"GET","Requests/s":"1.19","# requests":"71","Average Content Size":"19"},{"Name":"Total","# failures":"0","Max response time":"1360","Median response time":"810","Average response time":"820","Min response time":"341","Method":"None","Requests/s":"2.44","# requests":"145","Average Content Size":"19"}],"Duration":121052659274},"Type":"LocustBatchExperimentResult"}},{"bench":{"namespaces":[{"name":"gold","chart":{"Name":"my-app","DirPath":"/exp/conf/helm/exp2app"},"config":{"Settings":[{"Parameter":{"Name":"worker1CPU","Resource":"","Searchspace":{"Min":2200,"Max":2200,"Granularity":1},"Prefix":"","Suffix":"m"},"Value":{"Value":2200,"Type":"int"}},{"Parameter":{"Name":"worker1Replicas","Resource":"","Searchspace":{"Min":0,"Max":0,"Granularity":1},"Prefix":"","Suffix":""},"Value":{"Value":0,"Type":"int"}},{"Parameter":{"Name":"worker2CPU","Resource":"","Searchspace":{"Min":750,"Max":750,"Granularity":1},"Prefix":"","Suffix":"m"},"Value":{"Value":750,"Type":"int"}},{"Parameter":{"Name":"worker2Replicas","Resource":"","Searchspace":{"Min":1,"Max":1,"Granularity":1},"Prefix":"","Suffix":""},"Value":{"Value":1,"Type":"int"}},{"Parameter":{"Name":"worker3CPU","Resource":"","Searchspace":{"Min":250,"Max":250,"Granularity":1},"Prefix":"","Suffix":"m"},"Value":{"Value":250,"Type":"int"}},{"Parameter":{"Name":"worker3Replicas","Resource":"","Searchspace":{"Min":0,"Max":1,"Granularity":1},"Prefix":"","Suffix":""},"Value":{"Value":1,"Type":"int"}},{"Parameter":{"Name":"demoCPU","Resource":"","Searchspace":{"Min":800,"Max":800,"Granularity":100},"Prefix":"","Suffix":"m"},"Value":{"Value":800,"Type":"int"}}]}}],"experiment":{"Iteration":0,"Sample":1,"Locustconfig":{"Name":"","ScriptPath":"/tmp/locustwrap/locust_exp.py","Users":2,"HatchRate":2,"DurationInSeconds":60},"OutputDir":"/exp/Results/exp3/gold/2_tenants-ex1/op/","Type":"LocustBatchExperiment"}},"result":{"Results":{"name":"","Distribution":[{"Name":"GET gold-0","# requests":"53","50%":"1100","66%":"1300","75%":"1400","80%":"1500","90%":"1800","95%":"2100","98%":"2400","99%":"2400","100%":"2400"},{"Name":"GET gold-1","# requests":"56","50%":"840","66%":"1300","75%":"1500","80%":"1600","90%":"1800","95%":"2300","98%":"2300","99%":"2400","100%":"2400"},{"Name":"Total","# requests":"109","50%":"920","66%":"1300","75%":"1400","80%":"1600","90%":"1800","95%":"2100","98%":"2400","99%":"2400","100%":"2400"}],"Requests":[{"Name":"gold-0","# failures":"0","Max response time":"2421","Median response time":"1100","Average response time":"1124","Min response time":"418","Method":"GET","Requests/s":"0.9","# requests":"53","Average Content Size":"19"},{"Name":"gold-1","# failures":"0","Max response time":"2417","Median response time":"820","Average response time":"1051","Min response time":"395","Method":"GET","Requests/s":"0.95","# requests":"56","Average Content Size":"19"},{"Name":"Total","# failures":"0","Max response time":"2421","Median response time":"920","Average response time":"1086","Min response time":"395","Method":"None","Requests/s":"1.86","# requests":"109","Average Content Size":"19"}],"Duration":121073006408},"Type":"LocustBatchExperimentResult"}}]