[{"Name": "GET gold-0", "100%": "4100", "50%": "2700", "# requests": "23", "80%": "3800", "99%": "4100", "75%": "3600", "90%": "4000", "66%": "3500", "95%": "4100", "98%": "4100"}, {"Name": "GET gold-1", "100%": "4200", "50%": "2600", "# requests": "23", "80%": "3800", "99%": "4200", "75%": "3500", "90%": "4100", "66%": "3400", "95%": "4100", "98%": "4200"}, {"Name": "GET gold-2", "100%": "4200", "50%": "2800", "# requests": "22", "80%": "3700", "99%": "4200", "75%": "3600", "90%": "4000", "66%": "3500", "95%": "4100", "98%": "4200"}, {"Name": "Total", "100%": "4200", "50%": "2700", "# requests": "68", "80%": "3800", "99%": "4200", "75%": "3600", "90%": "4100", "66%": "3400", "95%": "4100", "98%": "4200"}]